<?xml version="1.0" encoding="utf-8"?>
<databaseChangeLog
    xmlns="http://www.liquibase.org/xml/ns/dbchangelog"
    xmlns:ext="http://www.liquibase.org/xml/ns/dbchangelog-ext"
    xmlns:xsi="http://www.w3.org/2001/XMLSchema-instance"
    xsi:schemaLocation="http://www.liquibase.org/xml/ns/dbchangelog http://www.liquibase.org/xml/ns/dbchangelog/dbchangelog-4.3.xsd
                        http://www.liquibase.org/xml/ns/dbchangelog-ext http://www.liquibase.org/xml/ns/dbchangelog/dbchangelog-ext.xsd">

    <!--
        Added the entity DocumentFreeText.
    -->
    <changeSet id="20210817165117-1" author="jhipster">
        <createTable tableName="document_free_text" remarks="free texts objects">
            <column name="id" type="bigint" autoIncrement="true">
                <constraints primaryKey="true" nullable="false"/>
            </column>
            <column name="text" type="varchar(255)" remarks="displayed text">
                <constraints nullable="true" />
            </column>
            <column name="font_size" type="integer" remarks="font size of displayed text (min: 1; max: 50)">
                <constraints nullable="true" />
            </column>
            <column name="position_x" type="double" remarks="The x position of the free text">
                <constraints nullable="true" />
            </column>
            <column name="position_y" type="double" remarks="The y position of the free text">
                <constraints nullable="true" />
            </column>
            <column name="page_no" type="integer" remarks="which page text is displayed on">
                <constraints nullable="true" />
            </column>
            <column name="document_letter_id" type="bigint">
                <constraints nullable="true" />
            </column>
            <column name="delivery_note_id" type="bigint">
                <constraints nullable="true" />
            </column>
            <column name="invoice_id" type="bigint">
                <constraints nullable="true" />
            </column>
            <column name="offer_id" type="bigint">
                <constraints nullable="true" />
            </column>
            <column name="order_confirmation_id" type="bigint">
                <constraints nullable="true" />
            </column>
            <!-- jhipster-needle-liquibase-add-column - JHipster will add columns here -->
        </createTable>
    </changeSet>

    <!-- jhipster-needle-liquibase-add-changeset - JHipster will add changesets here -->

    <!--
        Load sample data generated with Faker.js
        - This data can be easily edited using a CSV editor (or even MS Excel) and
          is located in the 'src/main/resources/config/liquibase/fake-data' directory
        - By default this data is applied when running with the JHipster 'dev' profile.
          This can be customized by adding or removing 'faker' in the 'spring.liquibase.contexts'
          Spring Boot configuration key.
    -->
    <changeSet id="20210817165117-1-data" author="jhipster" context="faker">
        <loadData
                  file="config/liquibase/fake-data/document_free_text.csv"
                  separator=";"
                  tableName="document_free_text">
            <column name="id" type="numeric"/>
            <column name="text" type="string"/>
            <column name="font_size" type="numeric"/>
            <column name="position_x" type="numeric"/>
            <column name="position_y" type="numeric"/>
            <column name="page_no" type="numeric"/>
            <!-- jhipster-needle-liquibase-add-loadcolumn - JHipster (and/or extensions) can add load columns here -->
        </loadData>
    </changeSet>
</databaseChangeLog>
